{
  "data": {
    "allCurrencies": 36834,
    "activeCurrencies": 4817,
    "activeMarkets": 47077,
    "btcDominance": 56.177067,
    "btcDominanceChange": 0.47,
    "ethDominance": 10.1,
    "ethDominanceChange": 2.12,
    "investmentActivity": -23,
    "totalVolume24h": "408622777711",
    "totalVolume24hChange": 807.8,
    "totalMarketCap": "2451405717623",
    "totalMarketCapChange": 3.51,
    "fearGreed": 9,
    "fearGreedChange": 4,
    "altcoinIndex": 29,
    "altcoinIndexChange": -6
  },
  "status": {
    "usedCredits": 1
  }
}