{
  "data": {
    "allCurrencies": 36444,
    "activeCurrencies": 5118,
    "activeMarkets": 46616,
    "btcDominance": 57.174034,
    "btcDominanceChange": 0.15,
    "ethDominance": 11.98,
    "ethDominanceChange": 1.87,
    "investmentActivity": -46,
    "totalVolume24h": "79223355137",
    "totalVolume24hChange": 14.1,
    "totalMarketCap": "3322659662057",
    "totalMarketCapChange": 3.3,
    "fearGreed": 48,
    "fearGreedChange": 22,
    "altcoinIndex": 33,
    "altcoinIndexChange": 0
  },
  "status": {
    "usedCredits": 1
  }
}