{
  "data": {
    "allCurrencies": 36311,
    "activeCurrencies": 4989,
    "activeMarkets": 45287,
    "btcDominance": 57.42864,
    "btcDominanceChange": 0.03,
    "ethDominance": 11.65,
    "ethDominanceChange": 0.17,
    "investmentActivity": -27,
    "totalVolume24h": "55770777039",
    "totalVolume24hChange": 135.25,
    "totalMarketCap": "3036696831371",
    "totalMarketCapChange": -0.22,
    "fearGreed": 24,
    "fearGreedChange": 0,
    "altcoinIndex": 15,
    "altcoinIndexChange": -2
  },
  "status": {
    "usedCredits": 1
  }
}