{
  "data": {
    "allCurrencies": 37497,
    "activeCurrencies": 5157,
    "activeMarkets": 49039,
    "btcDominance": 57.8642,
    "btcDominanceChange": 1.05,
    "ethDominance": 10.57,
    "ethDominanceChange": 0.57,
    "investmentActivity": -27,
    "totalVolume24h": "45293585732",
    "totalVolume24hChange": 20.54,
    "totalMarketCap": "2746561465829",
    "totalMarketCapChange": 3.69,
    "fearGreed": 32,
    "fearGreedChange": -1,
    "altcoinIndex": 36,
    "altcoinIndexChange": 0
  },
  "status": {
    "usedCredits": 1
  }
}