{
  "data": {
    "allCurrencies": 37407,
    "activeCurrencies": 4886,
    "activeMarkets": 48331,
    "btcDominance": 57.11584,
    "btcDominanceChange": 0.89,
    "ethDominance": 10.55,
    "ethDominanceChange": -1.59,
    "investmentActivity": -14,
    "totalVolume24h": "35245420710",
    "totalVolume24hChange": -12.55,
    "totalMarketCap": "2493320556749",
    "totalMarketCapChange": -1.42,
    "fearGreed": 14,
    "fearGreedChange": -3,
    "altcoinIndex": 34,
    "altcoinIndexChange": -3
  },
  "status": {
    "usedCredits": 1
  }
}