{
  "data": {
    "allCurrencies": 36061,
    "activeCurrencies": 5004,
    "activeMarkets": 45278,
    "btcDominance": 55.640022,
    "btcDominanceChange": 0.2,
    "ethDominance": 10.88,
    "ethDominanceChange": -0.82,
    "investmentActivity": -33,
    "totalVolume24h": "75353487410",
    "totalVolume24hChange": -7.54,
    "totalMarketCap": "3103238504436",
    "totalMarketCapChange": -1.06,
    "fearGreed": 23,
    "fearGreedChange": -1,
    "altcoinIndex": 20,
    "altcoinIndexChange": -2
  },
  "status": {
    "usedCredits": 1
  }
}