{
  "data": {
    "allCurrencies": 37076,
    "activeCurrencies": 4703,
    "activeMarkets": 46284,
    "btcDominance": 56.598732,
    "btcDominanceChange": -0.15,
    "ethDominance": 10.01,
    "ethDominanceChange": 0.2,
    "investmentActivity": -36,
    "totalVolume24h": "45045216940",
    "totalVolume24hChange": 19.68,
    "totalMarketCap": "2530669994542",
    "totalMarketCapChange": 2.8,
    "fearGreed": 15,
    "fearGreedChange": -3,
    "altcoinIndex": 40,
    "altcoinIndexChange": -1
  },
  "status": {
    "usedCredits": 1
  }
}