{
  "data": {
    "allCurrencies": 37964,
    "activeCurrencies": 4821,
    "activeMarkets": 49251,
    "btcDominance": 56.393112,
    "btcDominanceChange": 0.55,
    "ethDominance": 9.22,
    "ethDominanceChange": 1.1,
    "investmentActivity": -16,
    "totalVolume24h": "22225789367",
    "totalVolume24hChange": -13.79,
    "totalMarketCap": "2281125027867",
    "totalMarketCapChange": 1.22,
    "fearGreed": 23,
    "fearGreedChange": 9,
    "altcoinIndex": 43,
    "altcoinIndexChange": -6
  },
  "status": {
    "usedCredits": 1
  }
}