{
  "data": {
    "allCurrencies": 37562,
    "activeCurrencies": 4803,
    "activeMarkets": 48018,
    "btcDominance": 58.67441,
    "btcDominanceChange": -0.05,
    "ethDominance": 10.47,
    "ethDominanceChange": 0.58,
    "investmentActivity": -45,
    "totalVolume24h": "20194915707",
    "totalVolume24hChange": 4.39,
    "totalMarketCap": "2687019968735",
    "totalMarketCapChange": 0.46,
    "fearGreed": 47,
    "fearGreedChange": 8,
    "altcoinIndex": 36,
    "altcoinIndexChange": 0
  },
  "status": {
    "usedCredits": 1
  }
}