[
  {
    "symbol": "BTC",
    "name": "Bitcoin",
    "price": "79568.89024481639",
    "h24": "-2.037844808890533"
  },
  {
    "symbol": "ETH",
    "name": "Ethereum",
    "price": "2256.008165861463",
    "h24": "-2.7906427984736983"
  },
  {
    "symbol": "SOL",
    "name": "Solana",
    "price": "90.734883736072",
    "h24": "-5.214840423974435"
  },
  {
    "symbol": "BNB",
    "name": "BNB",
    "price": "669.95515079634",
    "h24": "-2.1793807967199794"
  },
  {
    "symbol": "KITE",
    "name": "KITE AI",
    "price": "0.225088386877",
    "h24": "9.814122110728654"
  },
  {
    "symbol": "H",
    "name": "Humanity Protocol",
    "price": "0.261301850908",
    "h24": "6.363728616522882"
  },
  {
    "symbol": "STABLE",
    "name": "Stable",
    "price": "0.039543719498",
    "h24": "5.161703478113525"
  },
  {
    "symbol": "QNT",
    "name": "Quant",
    "price": "77.432407668269",
    "h24": "4.500484295537667"
  },
  {
    "symbol": "CC",
    "name": "Canton Network",
    "price": "0.159075546221",
    "h24": "4.260403104559092"
  },
  {
    "symbol": "UB",
    "name": "Unibase",
    "price": "0.210202705227",
    "h24": "2.7382033660070806"
  },
  {
    "symbol": "M",
    "name": "MemeCore",
    "price": "3.346599861738",
    "h24": "1.8345723402144805"
  },
  {
    "symbol": "XDC",
    "name": "XDC Network",
    "price": "0.033274091055",
    "h24": "1.8025483668572737"
  },
  {
    "symbol": "EDGE",
    "name": "edgeX",
    "price": "1.366764577795",
    "h24": "1.37528769934062"
  },
  {
    "symbol": "TRX",
    "name": "TRON",
    "price": "0.352848849416",
    "h24": "0.6664809406574645"
  },
  {
    "symbol": "BGB",
    "name": "Bitget Token",
    "price": "2.092201654213",
    "h24": "0.38419492768816677"
  },
  {
    "symbol": "HTX",
    "name": "HTX DAO",
    "price": "0.000001969067",
    "h24": "0.302987236127815"
  },
  {
    "symbol": "FGI",
    "name": "Fear & Greed Index",
    "price": 34,
    "h24": 36
  }
]