[
  {
    "symbol": "BTC",
    "name": "Bitcoin",
    "price": "108704.206555942150",
    "h24": "-8.793406620353208"
  },
  {
    "symbol": "ETH",
    "name": "Ethereum",
    "price": "3868.100617675959",
    "h24": "-12.16958722780162"
  },
  {
    "symbol": "SOL",
    "name": "Solana",
    "price": "192.002597195417",
    "h24": "-1.4763529204419956"
  },
  {
    "symbol": "BNB",
    "name": "BNB",
    "price": "1101.694199969275",
    "h24": "-0.8841419123687481"
  },
  {
    "symbol": "ZEC",
    "name": "Zcash",
    "price": "341.027426216192",
    "h24": "7.765358792360985"
  },
  {
    "symbol": "TRUMP",
    "name": "OFFICIAL TRUMP",
    "price": "8.144697692819",
    "h24": "7.145687815005543"
  },
  {
    "symbol": "AERO",
    "name": "Aerodrome",
    "price": "1.034317520065",
    "h24": "4.624033831094089"
  },
  {
    "symbol": "M",
    "name": "MemeCore",
    "price": "2.356612871244",
    "h24": "4.030329987242993"
  },
  {
    "symbol": "HBAR",
    "name": "Hedera",
    "price": "0.200302140676",
    "h24": "3.1201380941345667"
  },
  {
    "symbol": "PUMP",
    "name": "pump.fun",
    "price": "0.005091100067",
    "h24": "3.1185910129822054"
  },
  {
    "symbol": "SKY",
    "name": "Sky",
    "price": "0.059446690006",
    "h24": "1.8254122859208568"
  },
  {
    "symbol": "TAO",
    "name": "Bittensor",
    "price": "439.781320484683",
    "h24": "1.1556408069748298"
  },
  {
    "symbol": "QNT",
    "name": "Quant",
    "price": "80.239228187915",
    "h24": "0.878382518113626"
  },
  {
    "symbol": "BDX",
    "name": "Beldex",
    "price": "0.079326234379",
    "h24": "0.7389730937595592"
  },
  {
    "symbol": "XAUT",
    "name": "Tether Gold",
    "price": "3970.650753300211",
    "h24": "0.23085287759582107"
  },
  {
    "symbol": "PAXG",
    "name": "PAX Gold",
    "price": "3971.317483484592",
    "h24": "0.20397718326612185"
  },
  {
    "symbol": "FGI",
    "name": "Fear & Greed Index",
    "price": 34,
    "h24": 32
  }
]