[
  {
    "symbol": "BTC",
    "name": "Bitcoin",
    "price": "67907.19871850865",
    "h24": "5.95556008167538"
  },
  {
    "symbol": "ETH",
    "name": "Ethereum",
    "price": "2035.448454286723",
    "h24": "9.752909862323126"
  },
  {
    "symbol": "SOL",
    "name": "Solana",
    "price": "87.193241664525",
    "h24": "11.87165555922651"
  },
  {
    "symbol": "BNB",
    "name": "BNB",
    "price": "624.374824664747",
    "h24": "6.308494066899764"
  },
  {
    "symbol": "FIL",
    "name": "Filecoin",
    "price": "1.081070707259",
    "h24": "22.933947788374695"
  },
  {
    "symbol": "DOT",
    "name": "Polkadot",
    "price": "1.527355280296",
    "h24": "21.691345598520847"
  },
  {
    "symbol": "MORPHO",
    "name": "Morpho",
    "price": "1.896584524102",
    "h24": "18.75810978372115"
  },
  {
    "symbol": "UNI",
    "name": "Uniswap",
    "price": "3.970620689911",
    "h24": "17.71556161345525"
  },
  {
    "symbol": "APT",
    "name": "Aptos",
    "price": "0.978456511327",
    "h24": "17.606787043336915"
  },
  {
    "symbol": "VIRTUAL",
    "name": "Virtuals Protocol",
    "price": "0.696501589787",
    "h24": "15.274356250972353"
  },
  {
    "symbol": "AVAX",
    "name": "Avalanche",
    "price": "9.637553263995",
    "h24": "14.992664695080515"
  },
  {
    "symbol": "LINK",
    "name": "ChainLink",
    "price": "9.41044238759",
    "h24": "13.936025029016479"
  },
  {
    "symbol": "NEAR",
    "name": "Near Protocol",
    "price": "1.120235299075",
    "h24": "13.72763063871355"
  },
  {
    "symbol": "LTC",
    "name": "Litecoin",
    "price": "58.080123734882",
    "h24": "12.947617974822025"
  },
  {
    "symbol": "ADA",
    "name": "Cardano",
    "price": "0.294448477592",
    "h24": "12.674954168321195"
  },
  {
    "symbol": "ETC",
    "name": "Ethereum Classic",
    "price": "9.361391676049",
    "h24": "11.805202457166294"
  },
  {
    "symbol": "FGI",
    "name": "Fear & Greed Index",
    "price": 11,
    "h24": 36
  }
]