[
  {
    "symbol": "BTC",
    "name": "Bitcoin",
    "price": "72246.0182325426",
    "h24": "1.3033197012553421"
  },
  {
    "symbol": "ETH",
    "name": "Ethereum",
    "price": "2222.18877435673",
    "h24": "0.33871866999843475"
  },
  {
    "symbol": "SOL",
    "name": "Solana",
    "price": "83.85048594121",
    "h24": "0.697742609761674"
  },
  {
    "symbol": "BNB",
    "name": "BNB",
    "price": "605.704251287162",
    "h24": "-0.031061093719451403"
  },
  {
    "symbol": "SIREN",
    "name": "SIREN",
    "price": "0.703527929443",
    "h24": "19.7339310669466"
  },
  {
    "symbol": "RAIN",
    "name": "Rain",
    "price": "0.008042474986",
    "h24": "8.44996132273993"
  },
  {
    "symbol": "MORPHO",
    "name": "Morpho",
    "price": "1.835082036047",
    "h24": "6.774367927851245"
  },
  {
    "symbol": "JST",
    "name": "Just",
    "price": "0.069101777247",
    "h24": "6.426010543530036"
  },
  {
    "symbol": "ARB",
    "name": "Arbitrum",
    "price": "0.10410405702",
    "h24": "3.3469546544977047"
  },
  {
    "symbol": "NEAR",
    "name": "Near Protocol",
    "price": "1.387453143437",
    "h24": "3.052701877149753"
  },
  {
    "symbol": "TON",
    "name": "Toncoin",
    "price": "1.291082257059",
    "h24": "2.9952067403087628"
  },
  {
    "symbol": "CHZ",
    "name": "Chiliz",
    "price": "0.039320956197",
    "h24": "2.723356519977265"
  },
  {
    "symbol": "HYPE",
    "name": "Hyperliquid",
    "price": "39.626680866203",
    "h24": "2.466640563935443"
  },
  {
    "symbol": "ATOM",
    "name": "Cosmos Hub",
    "price": "1.820745783169",
    "h24": "2.1297686947459122"
  },
  {
    "symbol": "CC",
    "name": "Canton Network",
    "price": "0.145862134284",
    "h24": "2.0628294432887504"
  },
  {
    "symbol": "NEXO",
    "name": "Nexo",
    "price": "0.888478850502",
    "h24": "1.9677584708331346"
  },
  {
    "symbol": "FGI",
    "name": "Fear & Greed Index",
    "price": 14,
    "h24": 35
  }
]