[
  {
    "symbol": "BTC",
    "name": "Bitcoin",
    "price": "78103.23555401582",
    "h24": "-0.11297032389773014"
  },
  {
    "symbol": "ETH",
    "name": "Ethereum",
    "price": "2183.899460697801",
    "h24": "0.264587589933736"
  },
  {
    "symbol": "SOL",
    "name": "Solana",
    "price": "86.219275517063",
    "h24": "-0.6038638150679447"
  },
  {
    "symbol": "BNB",
    "name": "BNB",
    "price": "651.319862336919",
    "h24": "-0.7971180538430107"
  },
  {
    "symbol": "HYPE",
    "name": "Hyperliquid",
    "price": "44.515376977376",
    "h24": "8.285375152910795"
  },
  {
    "symbol": "VVV",
    "name": "Venice Token",
    "price": "14.196776681055",
    "h24": "6.243511174235445"
  },
  {
    "symbol": "币安人生",
    "name": "币安人生 (Binancelive)",
    "price": "0.41637539245",
    "h24": "5.672738613664421"
  },
  {
    "symbol": "DEXE",
    "name": "DeXe",
    "price": "13.309911001962",
    "h24": "2.9598612056026323"
  },
  {
    "symbol": "RAIN",
    "name": "Rain",
    "price": "0.007499619585",
    "h24": "2.534953807320024"
  },
  {
    "symbol": "ATOM",
    "name": "Cosmos Hub",
    "price": "2.044253991689",
    "h24": "2.301140646922163"
  },
  {
    "symbol": "CC",
    "name": "Canton Network",
    "price": "0.153509665252",
    "h24": "1.9835745788954091"
  },
  {
    "symbol": "XMR",
    "name": "Monero",
    "price": "393.732585766906",
    "h24": "1.6355765702394298"
  },
  {
    "symbol": "NEXO",
    "name": "Nexo",
    "price": "0.880064966761",
    "h24": "1.526903295604809"
  },
  {
    "symbol": "NEAR",
    "name": "Near Protocol",
    "price": "1.516794539175",
    "h24": "1.061357510796628"
  },
  {
    "symbol": "POL",
    "name": "POL (ex-MATIC)",
    "price": "0.091742420252",
    "h24": "0.9390724988529076"
  },
  {
    "symbol": "ZEC",
    "name": "Zcash",
    "price": "517.032960570466",
    "h24": "0.885686146378354"
  },
  {
    "symbol": "FGI",
    "name": "Fear & Greed Index",
    "price": 27,
    "h24": 29
  }
]