[
  {
    "symbol": "BTC",
    "name": "Bitcoin",
    "price": "101728.54685228642",
    "h24": "-14.646226656518932"
  },
  {
    "symbol": "ETH",
    "name": "Ethereum",
    "price": "3375.660075998589",
    "h24": "-23.35111023256634"
  },
  {
    "symbol": "SOL",
    "name": "Solana",
    "price": "156.126634513963",
    "h24": "-4.5324501276963645"
  },
  {
    "symbol": "BNB",
    "name": "BNB",
    "price": "985.601526596939",
    "h24": "-1.12693327077523"
  },
  {
    "symbol": "XMR",
    "name": "Monero",
    "price": "391.516752967083",
    "h24": "6.398099976035466"
  },
  {
    "symbol": "NEAR",
    "name": "Near Protocol",
    "price": "2.879131206645",
    "h24": "4.977021605537993"
  },
  {
    "symbol": "MNT",
    "name": "Mantle",
    "price": "1.321892638102",
    "h24": "3.690093089753684"
  },
  {
    "symbol": "KCS",
    "name": "KuCoin Token",
    "price": "12.832071419334",
    "h24": "0.8299944942803917"
  },
  {
    "symbol": "MORPHO",
    "name": "Morpho",
    "price": "1.806045511961",
    "h24": "0.8005218177778838"
  },
  {
    "symbol": "FTN",
    "name": "Fasttoken",
    "price": "2.004129393724",
    "h24": "0.24846903477788945"
  },
  {
    "symbol": "LTC",
    "name": "Litecoin",
    "price": "101.627678474527",
    "h24": "0.22794308575655609"
  },
  {
    "symbol": "USDT",
    "name": "Tether",
    "price": "0.999687311468",
    "h24": "0.020927270238351607"
  },
  {
    "symbol": "RLUSD",
    "name": "Ripple USD",
    "price": "1.000000336861",
    "h24": "0.01480609619345498"
  },
  {
    "symbol": "USD1",
    "name": "USD1",
    "price": "0.999157458802",
    "h24": "0.012567962233555538"
  },
  {
    "symbol": "DAI",
    "name": "Dai",
    "price": "0.999840582328",
    "h24": "0.007132646398948757"
  },
  {
    "symbol": "USDG",
    "name": "Global Dollar",
    "price": "1.000052409747",
    "h24": "0.0030166764021422607"
  },
  {
    "symbol": "FGI",
    "name": "Fear & Greed Index",
    "price": 22,
    "h24": 34
  }
]