[
  {
    "symbol": "BTC",
    "name": "Bitcoin",
    "price": "108047.611116679440",
    "h24": "-9.344312929695946"
  },
  {
    "symbol": "ETH",
    "name": "Ethereum",
    "price": "3847.840394735389",
    "h24": "-12.629622764518388"
  },
  {
    "symbol": "SOL",
    "name": "Solana",
    "price": "184.911130831010",
    "h24": "-2.5409283336505086"
  },
  {
    "symbol": "BNB",
    "name": "BNB",
    "price": "1057.442124957479",
    "h24": "-3.8976050196748027"
  },
  {
    "symbol": "COAI",
    "name": "ChainOpera AI",
    "price": "8.566817029562",
    "h24": "66.63413246546452"
  },
  {
    "symbol": "2Z",
    "name": "DoubleZero",
    "price": "0.259251488602",
    "h24": "8.016683306841587"
  },
  {
    "symbol": "M",
    "name": "MemeCore",
    "price": "2.092336656323",
    "h24": "3.5980691144257784"
  },
  {
    "symbol": "USD1",
    "name": "USD1",
    "price": "1.000154199954",
    "h24": "0.03589918002104386"
  },
  {
    "symbol": "USDe",
    "name": "Ethena USDe",
    "price": "0.999650883462",
    "h24": "0.027131498771306814"
  },
  {
    "symbol": "USDT",
    "name": "Tether",
    "price": "1.000391873864",
    "h24": "0.016212205420235562"
  },
  {
    "symbol": "DAI",
    "name": "Dai",
    "price": "0.999994450104",
    "h24": "0.006231694299039855"
  },
  {
    "symbol": "USDC",
    "name": "USDC",
    "price": "0.999875958444",
    "h24": "0.0013807283291696244"
  },
  {
    "symbol": "RLUSD",
    "name": "Ripple USD",
    "price": "0.999872890397",
    "h24": "-0.005435878386103473"
  },
  {
    "symbol": "FDUSD",
    "name": "First Digital USD",
    "price": "0.997730150904",
    "h24": "-0.011050419403910033"
  },
  {
    "symbol": "BCH",
    "name": "Bitcoin Cash",
    "price": "479.497429575437",
    "h24": "-0.021533504601068156"
  },
  {
    "symbol": "USDG",
    "name": "Global Dollar",
    "price": "0.999675277789",
    "h24": "-0.04904917075358397"
  },
  {
    "symbol": "FGI",
    "name": "Fear & Greed Index",
    "price": 25,
    "h24": 29
  }
]