[
  {
    "symbol": "BTC",
    "name": "Bitcoin",
    "price": "77810.22412843507",
    "h24": "0.09566675223400742"
  },
  {
    "symbol": "ETH",
    "name": "Ethereum",
    "price": "2320.070642031378",
    "h24": "0.09137263359265684"
  },
  {
    "symbol": "SOL",
    "name": "Solana",
    "price": "86.622202359021",
    "h24": "1.0954975017381785"
  },
  {
    "symbol": "BNB",
    "name": "BNB",
    "price": "638.050054567443",
    "h24": "0.4318607126775889"
  },
  {
    "symbol": "ALGO",
    "name": "Algorand",
    "price": "0.116004525032",
    "h24": "8.341643520009233"
  },
  {
    "symbol": "ATOM",
    "name": "Cosmos Hub",
    "price": "2.052339120761",
    "h24": "4.725646087903042"
  },
  {
    "symbol": "CHZ",
    "name": "Chiliz",
    "price": "0.04993970864",
    "h24": "4.460942536172358"
  },
  {
    "symbol": "DEXE",
    "name": "DeXe",
    "price": "13.546737818138",
    "h24": "4.08975005163898"
  },
  {
    "symbol": "VVV",
    "name": "Venice Token",
    "price": "8.822506464598",
    "h24": "3.0170368489459416"
  },
  {
    "symbol": "TON",
    "name": "Toncoin",
    "price": "1.346000207234",
    "h24": "2.8418155457833283"
  },
  {
    "symbol": "TRUMP",
    "name": "OFFICIAL TRUMP",
    "price": "2.946173744241",
    "h24": "2.6530953584765746"
  },
  {
    "symbol": "HYPE",
    "name": "Hyperliquid",
    "price": "41.828766430448",
    "h24": "2.439521275994877"
  },
  {
    "symbol": "APT",
    "name": "Aptos",
    "price": "0.975921328967",
    "h24": "2.08683023450683"
  },
  {
    "symbol": "ZEC",
    "name": "Zcash",
    "price": "360.34402624262",
    "h24": "1.9610840912032637"
  },
  {
    "symbol": "DOT",
    "name": "Polkadot",
    "price": "1.268518136277",
    "h24": "1.8264913110180745"
  },
  {
    "symbol": "AAVE",
    "name": "Aave",
    "price": "96.106310270184",
    "h24": "1.671591920129856"
  },
  {
    "symbol": "FGI",
    "name": "Fear & Greed Index",
    "price": 31,
    "h24": 39
  }
]