[
  {
    "symbol": "BTC",
    "name": "Bitcoin",
    "price": "65916.74203640419",
    "h24": "-4.279830830020939"
  },
  {
    "symbol": "ETH",
    "name": "Ethereum",
    "price": "1983.02945524959",
    "h24": "-4.057756195047156"
  },
  {
    "symbol": "SOL",
    "name": "Solana",
    "price": "82.572657422601",
    "h24": "-4.644173384760579"
  },
  {
    "symbol": "BNB",
    "name": "BNB",
    "price": "609.790232363599",
    "h24": "-3.165332849545738"
  },
  {
    "symbol": "DEXE",
    "name": "DeXe",
    "price": "7.394804488649",
    "h24": "2.334451281904908"
  },
  {
    "symbol": "BCH",
    "name": "Bitcoin Cash",
    "price": "470.867129508226",
    "h24": "2.191530786959888"
  },
  {
    "symbol": "XAUT",
    "name": "Tether Gold",
    "price": "4490.09427914462",
    "h24": "2.0947463761420524"
  },
  {
    "symbol": "PAXG",
    "name": "PAX Gold",
    "price": "4497.084016941935",
    "h24": "2.060998760527399"
  },
  {
    "symbol": "ONDO",
    "name": "Ondo Finance",
    "price": "0.268645809518",
    "h24": "1.2588322171772348"
  },
  {
    "symbol": "M",
    "name": "MemeCore",
    "price": "2.184391504563",
    "h24": "0.5147680556911416"
  },
  {
    "symbol": "STABLE",
    "name": "Stable",
    "price": "0.026312671439",
    "h24": "0.36585885080350095"
  },
  {
    "symbol": "USD1",
    "name": "USD1",
    "price": "0.99944556563",
    "h24": "0.0017859724832515727"
  },
  {
    "symbol": "USDS",
    "name": "USDS",
    "price": "0.999644546925",
    "h24": "0.0004928776232748416"
  },
  {
    "symbol": "DAI",
    "name": "Dai",
    "price": "0.999372560662",
    "h24": "-0.011377799600844363"
  },
  {
    "symbol": "PYUSD",
    "name": "PayPal USD",
    "price": "0.999513847851",
    "h24": "-0.014349697403750148"
  },
  {
    "symbol": "USDG",
    "name": "Global Dollar",
    "price": "0.999831614662",
    "h24": "-0.014407091450598177"
  },
  {
    "symbol": "FGI",
    "name": "Fear & Greed Index",
    "price": 13,
    "h24": 46
  }
]