[
  {
    "symbol": "BTC",
    "name": "Bitcoin",
    "price": "65745.2412136499",
    "h24": "-3.4685121677051365"
  },
  {
    "symbol": "ETH",
    "name": "Ethereum",
    "price": "1924.347093946532",
    "h24": "-2.812490461376212"
  },
  {
    "symbol": "SOL",
    "name": "Solana",
    "price": "77.417072644255",
    "h24": "-4.1091483923477785"
  },
  {
    "symbol": "BNB",
    "name": "BNB",
    "price": "607.316078430729",
    "h24": "-1.3229969416247542"
  },
  {
    "symbol": "RIVER",
    "name": "River",
    "price": "21.557253850037",
    "h24": "24.95560853232273"
  },
  {
    "symbol": "STABLE",
    "name": "Stable",
    "price": "0.023085747386",
    "h24": "5.593611375838415"
  },
  {
    "symbol": "POL",
    "name": "POL (ex-MATIC)",
    "price": "0.094418794481",
    "h24": "4.884764154203912"
  },
  {
    "symbol": "pippin",
    "name": "Pippin",
    "price": "0.487967544449",
    "h24": "4.508321974544233"
  },
  {
    "symbol": "WLFI",
    "name": "World Liberty Financial",
    "price": "0.107126488738",
    "h24": "3.715490450080152"
  },
  {
    "symbol": "TON",
    "name": "Toncoin",
    "price": "1.379628317591",
    "h24": "3.2413652744320602"
  },
  {
    "symbol": "SEI",
    "name": "Sei",
    "price": "0.07351162368",
    "h24": "3.0102548600476315"
  },
  {
    "symbol": "ENA",
    "name": "Ethena",
    "price": "0.115799148072",
    "h24": "2.2784634542275235"
  },
  {
    "symbol": "TAO",
    "name": "Bittensor",
    "price": "151.497739727895",
    "h24": "2.1316872557039264"
  },
  {
    "symbol": "XDC",
    "name": "XDC Network",
    "price": "0.036079932246",
    "h24": "1.8723981298777568"
  },
  {
    "symbol": "NIGHT",
    "name": "Midnight Network",
    "price": "0.050206703989",
    "h24": "1.7944041190393467"
  },
  {
    "symbol": "CC",
    "name": "Canton Network",
    "price": "0.165132701306",
    "h24": "1.4077127443797373"
  },
  {
    "symbol": "FGI",
    "name": "Fear & Greed Index",
    "price": 5,
    "h24": 32
  }
]