[
  {
    "symbol": "BTC",
    "name": "Bitcoin",
    "price": "68493.73794609403",
    "h24": "1.4182350037488893"
  },
  {
    "symbol": "ETH",
    "name": "Ethereum",
    "price": "1989.387419119266",
    "h24": "1.3331254025582533"
  },
  {
    "symbol": "SOL",
    "name": "Solana",
    "price": "86.274900090843",
    "h24": "2.3263539128994997"
  },
  {
    "symbol": "BNB",
    "name": "BNB",
    "price": "627.902329422575",
    "h24": "0.759009378128759"
  },
  {
    "symbol": "ZRO",
    "name": "LayerZero",
    "price": "1.735705369142",
    "h24": "9.369374414215844"
  },
  {
    "symbol": "ETC",
    "name": "Ethereum Classic",
    "price": "9.238180249619",
    "h24": "7.469225163349937"
  },
  {
    "symbol": "MORPHO",
    "name": "Morpho",
    "price": "1.624867951721",
    "h24": "7.407964752762699"
  },
  {
    "symbol": "WLFI",
    "name": "World Liberty Financial",
    "price": "0.121308924169",
    "h24": "6.654012511131186"
  },
  {
    "symbol": "POL",
    "name": "POL (ex-MATIC)",
    "price": "0.111046589451",
    "h24": "5.826036742943804"
  },
  {
    "symbol": "AAVE",
    "name": "Aave",
    "price": "123.288512666405",
    "h24": "5.652809745879937"
  },
  {
    "symbol": "UNI",
    "name": "Uniswap",
    "price": "3.617192578175",
    "h24": "4.887815160989928"
  },
  {
    "symbol": "ARB",
    "name": "Arbitrum",
    "price": "0.099282295758",
    "h24": "3.7025072130533427"
  },
  {
    "symbol": "CAKE",
    "name": "PancakeSwap",
    "price": "1.333726606008",
    "h24": "3.4828938867071564"
  },
  {
    "symbol": "ICP",
    "name": "Internet Computer",
    "price": "2.232507931166",
    "h24": "3.3418267289417445"
  },
  {
    "symbol": "TAO",
    "name": "Bittensor",
    "price": "184.432401941353",
    "h24": "3.112878046839631"
  },
  {
    "symbol": "DCR",
    "name": "Decred",
    "price": "24.123351506491",
    "h24": "2.9539367842305557"
  },
  {
    "symbol": "FGI",
    "name": "Fear & Greed Index",
    "price": 8,
    "h24": 37
  }
]