[
  {
    "symbol": "BTC",
    "name": "Bitcoin",
    "price": "121256.058627208830",
    "h24": "1.7380318979560723"
  },
  {
    "symbol": "ETH",
    "name": "Ethereum",
    "price": "4322.860750812763",
    "h24": "-1.8436484393366768"
  },
  {
    "symbol": "SOL",
    "name": "Solana",
    "price": "222.679647804757",
    "h24": "0.8546391000975981"
  },
  {
    "symbol": "BNB",
    "name": "BNB",
    "price": "1251.197968488421",
    "h24": "0.9548728617940698"
  },
  {
    "symbol": "ZORA",
    "name": "Zora",
    "price": "0.119867326952",
    "h24": "104.67839759958221"
  },
  {
    "symbol": "GIGGLE",
    "name": "GiggleFund",
    "price": "119.033929491755",
    "h24": "45.197774789219416"
  },
  {
    "symbol": "DESO",
    "name": "Decentralized Social",
    "price": "7.628108053613",
    "h24": "45.02247868067536"
  },
  {
    "symbol": "DASH",
    "name": "Dash",
    "price": "44.905822998585",
    "h24": "43.351465686335665"
  },
  {
    "symbol": "RAIL",
    "name": "Railgun",
    "price": "3.922701754462",
    "h24": "41.60665528545896"
  },
  {
    "symbol": "ZEN",
    "name": "Horizen",
    "price": "15.164008222902",
    "h24": "32.72862197700344"
  },
  {
    "symbol": "ZEC",
    "name": "Zcash",
    "price": "234.746956272872",
    "h24": "27.058086765614664"
  },
  {
    "symbol": "SNX",
    "name": "Synthetix",
    "price": "1.377645385477",
    "h24": "26.599451520679594"
  },
  {
    "symbol": "COAI",
    "name": "ChainOpera AI",
    "price": "7.222574149183",
    "h24": "25.31167479231945"
  },
  {
    "symbol": "META",
    "name": "Meta DAO",
    "price": "6306.189495806481",
    "h24": "24.450148693812732"
  },
  {
    "symbol": "DCR",
    "name": "Decred",
    "price": "21.570174070398",
    "h24": "21.415500725173118"
  },
  {
    "symbol": "TAO",
    "name": "Bittensor",
    "price": "392.734617470936",
    "h24": "21.127518920012697"
  }
]