[
  {
    "symbol": "BTC",
    "name": "Bitcoin",
    "price": "88798.41490524597",
    "h24": "0.8095212213439663"
  },
  {
    "symbol": "ETH",
    "name": "Ethereum",
    "price": "3030.164535514944",
    "h24": "1.8334033372870866"
  },
  {
    "symbol": "SOL",
    "name": "Solana",
    "price": "126.353649321504",
    "h24": "0.8375930386610583"
  },
  {
    "symbol": "BNB",
    "name": "BNB",
    "price": "856.567555092807",
    "h24": "0.8689518549979816"
  },
  {
    "symbol": "BEAT",
    "name": "Audiera",
    "price": "4.063808220775",
    "h24": "52.41713262787247"
  },
  {
    "symbol": "NIGHT",
    "name": "Midnight Network",
    "price": "0.102303800849",
    "h24": "26.39275997167301"
  },
  {
    "symbol": "M",
    "name": "MemeCore",
    "price": "1.427176528221",
    "h24": "6.618183474232246"
  },
  {
    "symbol": "KAS",
    "name": "Kaspa",
    "price": "0.046869347165",
    "h24": "5.432194366556901"
  },
  {
    "symbol": "SKY",
    "name": "Sky",
    "price": "0.066421352123",
    "h24": "4.927553138732479"
  },
  {
    "symbol": "HYPE",
    "name": "Hyperliquid",
    "price": "24.817360533141",
    "h24": "3.3339136165964183"
  },
  {
    "symbol": "XMR",
    "name": "Monero",
    "price": "477.779795883464",
    "h24": "2.7405185594395447"
  },
  {
    "symbol": "VIRTUAL",
    "name": "Virtuals Protocol",
    "price": "0.728919231137",
    "h24": "2.659760814029235"
  },
  {
    "symbol": "PUMP",
    "name": "pump.fun",
    "price": "0.002010620629",
    "h24": "2.41498964720434"
  },
  {
    "symbol": "MORPHO",
    "name": "Morpho",
    "price": "1.242528307901",
    "h24": "2.1616347329290093"
  },
  {
    "symbol": "XAUT",
    "name": "Tether Gold",
    "price": "4428.480258230308",
    "h24": "1.9218467673170216"
  },
  {
    "symbol": "LDO",
    "name": "Lido",
    "price": "0.549462412086",
    "h24": "1.7411192264813515"
  },
  {
    "symbol": "FGI",
    "name": "Fear & Greed Index",
    "price": 25,
    "h24": 17
  }
]