[
  {
    "symbol": "BTC",
    "name": "Bitcoin",
    "price": "73511.63441184747",
    "h24": "-0.24215871919980575"
  },
  {
    "symbol": "ETH",
    "name": "Ethereum",
    "price": "2013.99281348071",
    "h24": "0.009285062990325683"
  },
  {
    "symbol": "SOL",
    "name": "Solana",
    "price": "82.485387489553",
    "h24": "0.39835842078065953"
  },
  {
    "symbol": "BNB",
    "name": "BNB",
    "price": "665.75135562183",
    "h24": "4.385918515376056"
  },
  {
    "symbol": "LAB",
    "name": "LAB",
    "price": "6.870387797954",
    "h24": "42.60500061833229"
  },
  {
    "symbol": "XLM",
    "name": "Stellar",
    "price": "0.259118917015",
    "h24": "25.284124962301455"
  },
  {
    "symbol": "INJ",
    "name": "Injective",
    "price": "6.942682576291",
    "h24": "15.32452193512708"
  },
  {
    "symbol": "XMR",
    "name": "Monero",
    "price": "398.666974459194",
    "h24": "11.569956676489165"
  },
  {
    "symbol": "H",
    "name": "Humanity Protocol",
    "price": "0.282894286221",
    "h24": "9.435818477047334"
  },
  {
    "symbol": "ALGO",
    "name": "Algorand",
    "price": "0.128333401796",
    "h24": "9.040539442334836"
  },
  {
    "symbol": "XDC",
    "name": "XDC Network",
    "price": "0.03401311679",
    "h24": "7.251678065761014"
  },
  {
    "symbol": "HYPE",
    "name": "Hyperliquid",
    "price": "65.443115396675",
    "h24": "6.294591213178744"
  },
  {
    "symbol": "JUP",
    "name": "Jupiter",
    "price": "0.186807047433",
    "h24": "6.257967462663972"
  },
  {
    "symbol": "TRUMP",
    "name": "OFFICIAL TRUMP",
    "price": "2.02327089584",
    "h24": "5.503343133261267"
  },
  {
    "symbol": "VET",
    "name": "VeChain",
    "price": "0.006232120051",
    "h24": "4.888906650318396"
  },
  {
    "symbol": "PENGU",
    "name": "Pudgy Penguins",
    "price": "0.008024011112",
    "h24": "3.956888397016119"
  },
  {
    "symbol": "FGI",
    "name": "Fear & Greed Index",
    "price": 23,
    "h24": 38
  }
]