[
  {
    "symbol": "BTC",
    "name": "Bitcoin",
    "price": "93058.58603400664",
    "h24": "-21.920623996086174"
  },
  {
    "symbol": "ETH",
    "name": "Ethereum",
    "price": "3199.713587215712",
    "h24": "-27.346211255792525"
  },
  {
    "symbol": "SOL",
    "name": "Solana",
    "price": "145.115677214406",
    "h24": "4.733744360139182"
  },
  {
    "symbol": "BNB",
    "name": "BNB",
    "price": "923.444143274724",
    "h24": "5.079756854213018"
  },
  {
    "symbol": "TEL",
    "name": "Telcoin",
    "price": "0.00621518078",
    "h24": "11.78770959075523"
  },
  {
    "symbol": "ENA",
    "name": "Ethena",
    "price": "0.299218328984",
    "h24": "11.2773080307745"
  },
  {
    "symbol": "ZEC",
    "name": "Zcash",
    "price": "343.242672278166",
    "h24": "10.65569153798163"
  },
  {
    "symbol": "CRV",
    "name": "Curve DAO",
    "price": "0.420907129996",
    "h24": "10.19894923735436"
  },
  {
    "symbol": "MNT",
    "name": "Mantle",
    "price": "1.130352899138",
    "h24": "9.776017347953418"
  },
  {
    "symbol": "LINK",
    "name": "ChainLink",
    "price": "14.794100944702",
    "h24": "8.73102696580454"
  },
  {
    "symbol": "AVAX",
    "name": "Avalanche",
    "price": "14.811908715416",
    "h24": "8.353513447579873"
  },
  {
    "symbol": "BCH",
    "name": "Bitcoin Cash",
    "price": "589.680413711254",
    "h24": "7.347371145387662"
  },
  {
    "symbol": "VIRTUAL",
    "name": "Virtuals Protocol",
    "price": "0.990714485576",
    "h24": "7.0795771595652"
  },
  {
    "symbol": "TAO",
    "name": "Bittensor",
    "price": "294.452478204255",
    "h24": "6.638242814209713"
  },
  {
    "symbol": "SHIB",
    "name": "SHIBA INU",
    "price": "0.000008989792",
    "h24": "5.551689412075229"
  },
  {
    "symbol": "LDO",
    "name": "Lido",
    "price": "0.653526024149",
    "h24": "5.287378424288286"
  },
  {
    "symbol": "FGI",
    "name": "Fear & Greed Index",
    "price": 26,
    "h24": 21
  }
]