[
  {
    "symbol": "BTC",
    "name": "Bitcoin",
    "price": "66455.00823142602",
    "h24": "2.890651128298744"
  },
  {
    "symbol": "ETH",
    "name": "Ethereum",
    "price": "1936.882776086522",
    "h24": "3.5233416028389812"
  },
  {
    "symbol": "SOL",
    "name": "Solana",
    "price": "78.359267016315",
    "h24": "2.2168092130261665"
  },
  {
    "symbol": "BNB",
    "name": "BNB",
    "price": "576.380084844151",
    "h24": "1.4052852930339075"
  },
  {
    "symbol": "ONDO",
    "name": "Ondo Finance",
    "price": "0.400288215498",
    "h24": "14.881149367016665"
  },
  {
    "symbol": "LDO",
    "name": "Lido",
    "price": "0.402144764346",
    "h24": "13.929630800149777"
  },
  {
    "symbol": "VVV",
    "name": "Venice AI",
    "price": "12.981118117042",
    "h24": "13.050595041036866"
  },
  {
    "symbol": "LIT",
    "name": "Lighter",
    "price": "2.383263228091",
    "h24": "9.785347601870635"
  },
  {
    "symbol": "ADA",
    "name": "Cardano",
    "price": "0.175490480364",
    "h24": "7.070202315188895"
  },
  {
    "symbol": "VIRTUAL",
    "name": "Virtuals Protocol",
    "price": "0.664054237474",
    "h24": "6.665305256827891"
  },
  {
    "symbol": "ENA",
    "name": "Ethena",
    "price": "0.086601952385",
    "h24": "6.33506129622767"
  },
  {
    "symbol": "SKY",
    "name": "Sky",
    "price": "0.064101107739",
    "h24": "6.062812882191946"
  },
  {
    "symbol": "UNI",
    "name": "Uniswap",
    "price": "3.701720208527",
    "h24": "5.950191878574712"
  },
  {
    "symbol": "DOT",
    "name": "Polkadot",
    "price": "0.85853290158",
    "h24": "5.7285383761418585"
  },
  {
    "symbol": "STABLE",
    "name": "Stable",
    "price": "0.037875169685",
    "h24": "5.71456638517212"
  },
  {
    "symbol": "FIL",
    "name": "Filecoin",
    "price": "0.750979136686",
    "h24": "5.069883124915317"
  },
  {
    "symbol": "FGI",
    "name": "Fear & Greed Index",
    "price": 25,
    "h24": 57
  }
]