[
  {
    "symbol": "BTC",
    "name": "Bitcoin",
    "price": "89756.79454299808",
    "h24": "-0.18465566056594676"
  },
  {
    "symbol": "ETH",
    "name": "Ethereum",
    "price": "2948.600721640502",
    "h24": "-2.891615483649359"
  },
  {
    "symbol": "SOL",
    "name": "Solana",
    "price": "129.264050757198",
    "h24": "-1.2366841719766473"
  },
  {
    "symbol": "BNB",
    "name": "BNB",
    "price": "887.465012975008",
    "h24": "0.14315454703849684"
  },
  {
    "symbol": "RIVER",
    "name": "River",
    "price": "58.099859798835",
    "h24": "31.961555760186044"
  },
  {
    "symbol": "RAIN",
    "name": "Rain",
    "price": "0.010047738503",
    "h24": "9.091904684085158"
  },
  {
    "symbol": "XDC",
    "name": "XDC Network",
    "price": "0.041920298544",
    "h24": "5.121042125713248"
  },
  {
    "symbol": "SKY",
    "name": "Sky",
    "price": "0.067301858391",
    "h24": "3.674555803688798"
  },
  {
    "symbol": "XAUT",
    "name": "Tether Gold",
    "price": "4919.987885751343",
    "h24": "2.8844740863814353"
  },
  {
    "symbol": "PAXG",
    "name": "PAX Gold",
    "price": "4935.70079160734",
    "h24": "2.792598539273162"
  },
  {
    "symbol": "BCH",
    "name": "Bitcoin Cash",
    "price": "600.816355199197",
    "h24": "2.212009388960577"
  },
  {
    "symbol": "CC",
    "name": "Canton Network",
    "price": "0.147711408959",
    "h24": "2.0904383757608054"
  },
  {
    "symbol": "TRX",
    "name": "TRON",
    "price": "0.304695614074",
    "h24": "2.060864316163365"
  },
  {
    "symbol": "IP",
    "name": "Story Protocol",
    "price": "2.444954646207",
    "h24": "1.8502913002057155"
  },
  {
    "symbol": "WLFI",
    "name": "World Liberty Financial",
    "price": "0.173847443449",
    "h24": "1.4342060787407718"
  },
  {
    "symbol": "M",
    "name": "MemeCore",
    "price": "1.660209478749",
    "h24": "0.9740568183386201"
  },
  {
    "symbol": "FGI",
    "name": "Fear & Greed Index",
    "price": 20,
    "h24": 31
  }
]