[
  {
    "symbol": "BTC",
    "name": "Bitcoin",
    "price": "86960.33287632093",
    "h24": "-27.037269558398904"
  },
  {
    "symbol": "ETH",
    "name": "Ethereum",
    "price": "2904.010613958297",
    "h24": "-34.06054388728686"
  },
  {
    "symbol": "SOL",
    "name": "Solana",
    "price": "135.295787205059",
    "h24": "4.040269566168895"
  },
  {
    "symbol": "BNB",
    "name": "BNB",
    "price": "846.868426761824",
    "h24": "0.8865953253675243"
  },
  {
    "symbol": "KAS",
    "name": "Kaspa",
    "price": "0.049879117584",
    "h24": "22.530762621078907"
  },
  {
    "symbol": "ENA",
    "name": "Ethena",
    "price": "0.276585875052",
    "h24": "13.595535335594596"
  },
  {
    "symbol": "QNT",
    "name": "Quant",
    "price": "85.621016363796",
    "h24": "10.309996785690485"
  },
  {
    "symbol": "IP",
    "name": "Story Protocol",
    "price": "2.542777928785",
    "h24": "10.267308509398068"
  },
  {
    "symbol": "PENGU",
    "name": "Pudgy Penguins",
    "price": "0.011277892822",
    "h24": "9.59880039674684"
  },
  {
    "symbol": "SUI",
    "name": "Sui",
    "price": "1.506450964132",
    "h24": "9.196582216334505"
  },
  {
    "symbol": "SPX",
    "name": "SPX6900",
    "price": "0.549791536533",
    "h24": "8.037549594838076"
  },
  {
    "symbol": "CRV",
    "name": "Curve DAO",
    "price": "0.415823118977",
    "h24": "7.0847880307767594"
  },
  {
    "symbol": "WLFI",
    "name": "World Liberty Financial",
    "price": "0.157980845895",
    "h24": "6.832984365631492"
  },
  {
    "symbol": "BONK",
    "name": "Bonk",
    "price": "0.000009687745",
    "h24": "6.66216797663764"
  },
  {
    "symbol": "XRP",
    "name": "XRP",
    "price": "2.210254147191",
    "h24": "5.866479971321558"
  },
  {
    "symbol": "JUP",
    "name": "Jupiter",
    "price": "0.24625019504",
    "h24": "4.7815616925412066"
  },
  {
    "symbol": "FGI",
    "name": "Fear & Greed Index",
    "price": 20,
    "h24": 25
  }
]