[
  {
    "symbol": "BTC",
    "name": "Bitcoin",
    "price": "68707.07957205013",
    "h24": "-2.9355251036028167"
  },
  {
    "symbol": "ETH",
    "name": "Ethereum",
    "price": "2061.201342896478",
    "h24": "-4.0068353382159785"
  },
  {
    "symbol": "SOL",
    "name": "Solana",
    "price": "86.425821656627",
    "h24": "-4.789094293809407"
  },
  {
    "symbol": "BNB",
    "name": "BNB",
    "price": "628.821260231694",
    "h24": "-2.0760842075010153"
  },
  {
    "symbol": "ONDO",
    "name": "Ondo Finance",
    "price": "0.280438610865",
    "h24": "4.211492951855609"
  },
  {
    "symbol": "NIGHT",
    "name": "Midnight Network",
    "price": "0.046102963872",
    "h24": "1.8987051696500024"
  },
  {
    "symbol": "CC",
    "name": "Canton Network",
    "price": "0.144489330736",
    "h24": "1.6731008717324327"
  },
  {
    "symbol": "ADI",
    "name": "ADI Chain",
    "price": "4.085742201067",
    "h24": "1.3662229473352496"
  },
  {
    "symbol": "ASTER",
    "name": "Aster (prev. Astherus)",
    "price": "0.670598226059",
    "h24": "1.1980386055164591"
  },
  {
    "symbol": "BDX",
    "name": "Beldex",
    "price": "0.083116956767",
    "h24": "0.30980172007575946"
  },
  {
    "symbol": "USDD",
    "name": "USDD",
    "price": "0.999267409728",
    "h24": "0.031223769985170024"
  },
  {
    "symbol": "USDS",
    "name": "USDS",
    "price": "0.9996858547",
    "h24": "0.008283573349132895"
  },
  {
    "symbol": "USDG",
    "name": "Global Dollar",
    "price": "0.999906134124",
    "h24": "0.002481002127848911"
  },
  {
    "symbol": "PYUSD",
    "name": "PayPal USD",
    "price": "0.999614950707",
    "h24": "-0.0018785033415604072"
  },
  {
    "symbol": "USD1",
    "name": "USD1",
    "price": "0.9993248759",
    "h24": "-0.004743870199317085"
  },
  {
    "symbol": "RLUSD",
    "name": "Ripple USD",
    "price": "0.999934383458",
    "h24": "-0.00942342549769865"
  },
  {
    "symbol": "FGI",
    "name": "Fear & Greed Index",
    "price": 13,
    "h24": 46
  }
]