[
  {
    "symbol": "BTC",
    "name": "Bitcoin",
    "price": "107420.078540526460",
    "h24": "-9.870834490535564"
  },
  {
    "symbol": "ETH",
    "name": "Ethereum",
    "price": "3877.515113937466",
    "h24": "-11.955818462606652"
  },
  {
    "symbol": "SOL",
    "name": "Solana",
    "price": "185.232173564740",
    "h24": "0.5797256597105501"
  },
  {
    "symbol": "BNB",
    "name": "BNB",
    "price": "1087.389274447420",
    "h24": "-5.799892460291606"
  },
  {
    "symbol": "KGEN",
    "name": "KGeN",
    "price": "0.494658570683",
    "h24": "39.441664912153726"
  },
  {
    "symbol": "ZORA",
    "name": "Zora",
    "price": "0.102454880422",
    "h24": "13.354288958758717"
  },
  {
    "symbol": "BANK",
    "name": "Lorenzo Protocol",
    "price": "0.152804759598",
    "h24": "13.20811709216222"
  },
  {
    "symbol": "ZIG",
    "name": "Zignaly",
    "price": "0.102146491404",
    "h24": "11.409963417433374"
  },
  {
    "symbol": "LA",
    "name": "Lagrange Labs",
    "price": "0.405245420921",
    "h24": "10.788316731547587"
  },
  {
    "symbol": "ZEC",
    "name": "Zcash",
    "price": "233.658538434156",
    "h24": "10.004461520350358"
  },
  {
    "symbol": "ENA",
    "name": "Ethena",
    "price": "0.443265812594",
    "h24": "9.281039283017643"
  },
  {
    "symbol": "KMNO",
    "name": "Kamino",
    "price": "0.066939256990",
    "h24": "9.044697907817447"
  },
  {
    "symbol": "BDCA",
    "name": "BitDCA",
    "price": "1.075745666785",
    "h24": "7.9064717614378015"
  },
  {
    "symbol": "ALEO",
    "name": "Aleo",
    "price": "0.239916608573",
    "h24": "7.690185471961017"
  },
  {
    "symbol": "AIA",
    "name": "DeAgentAI",
    "price": "0.958576688040",
    "h24": "7.18965171415736"
  },
  {
    "symbol": "DASH",
    "name": "Dash",
    "price": "45.502944105440",
    "h24": "7.161968872925779"
  },
  {
    "symbol": "FGI",
    "name": "Fear & Greed Index",
    "price": 22,
    "h24": 24
  }
]