[
  {
    "symbol": "BTC",
    "name": "Bitcoin",
    "price": "105671.23483301423",
    "h24": "-11.338174918005919"
  },
  {
    "symbol": "ETH",
    "name": "Ethereum",
    "price": "3583.6904285999",
    "h24": "-18.62750204755047"
  },
  {
    "symbol": "SOL",
    "name": "Solana",
    "price": "167.923322802607",
    "h24": "3.5386621750400167"
  },
  {
    "symbol": "BNB",
    "name": "BNB",
    "price": "993.747873554271",
    "h24": "-0.00826784750019929"
  },
  {
    "symbol": "STRK",
    "name": "StarkNet",
    "price": "0.189225792075",
    "h24": "36.34787086720972"
  },
  {
    "symbol": "WLFI",
    "name": "World Liberty Financial",
    "price": "0.159439433291",
    "h24": "27.856763400644333"
  },
  {
    "symbol": "PUMP",
    "name": "pump.fun",
    "price": "0.004509552971",
    "h24": "14.351977501463132"
  },
  {
    "symbol": "TRUMP",
    "name": "OFFICIAL TRUMP",
    "price": "8.593344709297",
    "h24": "13.295942961438648"
  },
  {
    "symbol": "HBAR",
    "name": "Hedera",
    "price": "0.192895889488",
    "h24": "10.536263511157339"
  },
  {
    "symbol": "RENDER",
    "name": "Render",
    "price": "2.625243406886",
    "h24": "10.336523755578892"
  },
  {
    "symbol": "XRP",
    "name": "XRP",
    "price": "2.53801906702",
    "h24": "9.626581373040093"
  },
  {
    "symbol": "INJ",
    "name": "Injective",
    "price": "8.006392271299",
    "h24": "8.758149923823774"
  },
  {
    "symbol": "XLM",
    "name": "Stellar",
    "price": "0.304948967496",
    "h24": "8.661973975007552"
  },
  {
    "symbol": "AAVE",
    "name": "Aave",
    "price": "223.32377645239",
    "h24": "6.84812886900257"
  },
  {
    "symbol": "FLR",
    "name": "Flare",
    "price": "0.016536635243",
    "h24": "5.745484584133873"
  },
  {
    "symbol": "PENGU",
    "name": "Pudgy Penguins",
    "price": "0.016038836198",
    "h24": "5.62392943952106"
  },
  {
    "symbol": "FGI",
    "name": "Fear & Greed Index",
    "price": 29,
    "h24": 28
  }
]