[
  {
    "symbol": "BTC",
    "name": "Bitcoin",
    "price": "77044.16408544405",
    "h24": "0.4063446349415894"
  },
  {
    "symbol": "ETH",
    "name": "Ethereum",
    "price": "2096.049893921767",
    "h24": "-1.160552678264206"
  },
  {
    "symbol": "SOL",
    "name": "Solana",
    "price": "85.051651577627",
    "h24": "-0.8969511598631956"
  },
  {
    "symbol": "BNB",
    "name": "BNB",
    "price": "656.445243293067",
    "h24": "-0.023163116160588037"
  },
  {
    "symbol": "STABLE",
    "name": "Stable",
    "price": "0.038105429938",
    "h24": "10.982257018116906"
  },
  {
    "symbol": "DEXE",
    "name": "DeXe",
    "price": "15.062861252512",
    "h24": "10.424220171051997"
  },
  {
    "symbol": "H",
    "name": "Humanity Protocol",
    "price": "0.232045300699",
    "h24": "10.045741673550227"
  },
  {
    "symbol": "VVV",
    "name": "Venice Token",
    "price": "19.193762890198",
    "h24": "6.860342864582531"
  },
  {
    "symbol": "MORPHO",
    "name": "Morpho",
    "price": "2.2379678464",
    "h24": "5.282243072040023"
  },
  {
    "symbol": "ONDO",
    "name": "Ondo Finance",
    "price": "0.442719516408",
    "h24": "4.6291875917906"
  },
  {
    "symbol": "XMR",
    "name": "Monero",
    "price": "396.147565896114",
    "h24": "2.876473818587475"
  },
  {
    "symbol": "EDGE",
    "name": "edgeX",
    "price": "1.32361510585",
    "h24": "2.7427502444052574"
  },
  {
    "symbol": "HYPE",
    "name": "Hyperliquid",
    "price": "61.462792287569",
    "h24": "2.562237294522232"
  },
  {
    "symbol": "ZEC",
    "name": "Zcash",
    "price": "649.012648855666",
    "h24": "2.2349444833028196"
  },
  {
    "symbol": "ASTER",
    "name": "Aster (prev. Astherus)",
    "price": "0.699002648238",
    "h24": "2.2244170354285004"
  },
  {
    "symbol": "BDX",
    "name": "Beldex",
    "price": "0.079945772372",
    "h24": "1.5260416420101912"
  },
  {
    "symbol": "FGI",
    "name": "Fear & Greed Index",
    "price": 30,
    "h24": 34
  }
]