[
  {
    "symbol": "BTC",
    "name": "Bitcoin",
    "price": "62832.13484709555",
    "h24": "1.3918087692705685"
  },
  {
    "symbol": "ETH",
    "name": "Ethereum",
    "price": "1643.729938422253",
    "h24": "-0.09365542323669844"
  },
  {
    "symbol": "SOL",
    "name": "Solana",
    "price": "65.196826944396",
    "h24": "0.47567003529107144"
  },
  {
    "symbol": "BNB",
    "name": "BNB",
    "price": "598.982752366345",
    "h24": "1.226055664960475"
  },
  {
    "symbol": "BEAT",
    "name": "Audiera",
    "price": "9.392806823699",
    "h24": "65.67046878390457"
  },
  {
    "symbol": "CRV",
    "name": "Curve DAO",
    "price": "0.249051788763",
    "h24": "17.544565130723"
  },
  {
    "symbol": "LAB",
    "name": "LAB",
    "price": "9.193334245908",
    "h24": "13.214197437158802"
  },
  {
    "symbol": "DEXE",
    "name": "DeXe",
    "price": "20.344508975122",
    "h24": "11.567152058408213"
  },
  {
    "symbol": "NIGHT",
    "name": "Midnight Network",
    "price": "0.033532679551",
    "h24": "8.445318920434275"
  },
  {
    "symbol": "ATOM",
    "name": "Cosmos Hub",
    "price": "1.931832520038",
    "h24": "7.838398748699808"
  },
  {
    "symbol": "XMR",
    "name": "Monero",
    "price": "349.939489699793",
    "h24": "7.429449286056449"
  },
  {
    "symbol": "KITE",
    "name": "KITE AI",
    "price": "0.186258079837",
    "h24": "5.102088347472162"
  },
  {
    "symbol": "SKY",
    "name": "Sky",
    "price": "0.057386488061",
    "h24": "3.4529656985187174"
  },
  {
    "symbol": "TRUMP",
    "name": "OFFICIAL TRUMP",
    "price": "1.70548726984",
    "h24": "2.464028030728975"
  },
  {
    "symbol": "LUNC",
    "name": "Terra Classic",
    "price": "0.000070368452",
    "h24": "2.0570066112843306"
  },
  {
    "symbol": "NEXO",
    "name": "Nexo",
    "price": "0.805621986519",
    "h24": "1.844076228228969"
  },
  {
    "symbol": "FGI",
    "name": "Fear & Greed Index",
    "price": 12,
    "h24": 47
  }
]