[
  {
    "symbol": "BTC",
    "name": "Bitcoin",
    "price": "112446.621475922180",
    "h24": "-5.653390914623525"
  },
  {
    "symbol": "ETH",
    "name": "Ethereum",
    "price": "3849.092775574096",
    "h24": "-12.601185777768618"
  },
  {
    "symbol": "SOL",
    "name": "Solana",
    "price": "184.459788192269",
    "h24": "-14.869921213945265"
  },
  {
    "symbol": "BNB",
    "name": "BNB",
    "price": "1153.748730661031",
    "h24": "-5.982922095855381"
  },
  {
    "symbol": "哈基米",
    "name": "哈基米",
    "price": "0.069560510950",
    "h24": "166.85034253862753"
  },
  {
    "symbol": "PAPARAZZI",
    "name": "Paparazzi",
    "price": "0.040204761759",
    "h24": "35.004493411183475"
  },
  {
    "symbol": "SKX",
    "name": "SKPANAX",
    "price": "1.237096215882",
    "h24": "31.607382510989357"
  },
  {
    "symbol": "ZEC",
    "name": "Zcash",
    "price": "275.665012372172",
    "h24": "24.047240447032642"
  },
  {
    "symbol": "AUKI",
    "name": "AUKI",
    "price": "0.023252979428",
    "h24": "18.3592873601333"
  },
  {
    "symbol": "M",
    "name": "MemeCore",
    "price": "2.271540686100",
    "h24": "17.368506111589813"
  },
  {
    "symbol": "MERL",
    "name": "Merlin Chain",
    "price": "0.396572637794",
    "h24": "15.323869220947998"
  },
  {
    "symbol": "GIGGLE",
    "name": "GiggleFund",
    "price": "126.116952905429",
    "h24": "14.274390884541358"
  },
  {
    "symbol": "QRL",
    "name": "Quantum Resistant Ledger",
    "price": "2.112776382692",
    "h24": "9.858938225059152"
  },
  {
    "symbol": "PTB",
    "name": "Portal",
    "price": "0.054662368999",
    "h24": "9.642342801102565"
  },
  {
    "symbol": "WKC",
    "name": "Wiki Cat",
    "price": "0.000000148739",
    "h24": "9.313059007694738"
  },
  {
    "symbol": "UDS",
    "name": "Undeads Games",
    "price": "2.374323128883",
    "h24": "7.374712805898579"
  }
]