[
  {
    "symbol": "BTC",
    "name": "Bitcoin",
    "price": "68142.4850608804",
    "h24": "-0.09281150895199326"
  },
  {
    "symbol": "ETH",
    "name": "Ethereum",
    "price": "2140.461915157712",
    "h24": "1.6495819355917998"
  },
  {
    "symbol": "SOL",
    "name": "Solana",
    "price": "80.976578091247",
    "h24": "-2.663817753256667"
  },
  {
    "symbol": "BNB",
    "name": "BNB",
    "price": "610.414224316447",
    "h24": "-1.3077233562058541"
  },
  {
    "symbol": "JST",
    "name": "Just",
    "price": "0.064530188192",
    "h24": "4.917498998459996"
  },
  {
    "symbol": "M",
    "name": "MemeCore",
    "price": "2.458735774873",
    "h24": "4.427318839745844"
  },
  {
    "symbol": "ALGO",
    "name": "Algorand",
    "price": "0.102283786767",
    "h24": "4.406734357470726"
  },
  {
    "symbol": "ZRO",
    "name": "LayerZero",
    "price": "1.977659812546",
    "h24": "3.940610808620453"
  },
  {
    "symbol": "FET",
    "name": "Artificial Superintelligence Alliance",
    "price": "0.242762004717",
    "h24": "3.9162281000974786"
  },
  {
    "symbol": "DEXE",
    "name": "DeXe",
    "price": "8.159067255055",
    "h24": "3.2757491257462656"
  },
  {
    "symbol": "TAO",
    "name": "Bittensor",
    "price": "315.714492104666",
    "h24": "2.6602953436563377"
  },
  {
    "symbol": "ADI",
    "name": "ADI Chain",
    "price": "4.292441440159",
    "h24": "2.498938450068295"
  },
  {
    "symbol": "VET",
    "name": "VeChain",
    "price": "0.006937765932",
    "h24": "2.142148937429439"
  },
  {
    "symbol": "ARB",
    "name": "Arbitrum",
    "price": "0.094698090223",
    "h24": "1.8257430955205247"
  },
  {
    "symbol": "NIGHT",
    "name": "Midnight Network",
    "price": "0.049622584491",
    "h24": "1.7780111466999"
  },
  {
    "symbol": "AVAX",
    "name": "Avalanche",
    "price": "9.121367108931",
    "h24": "1.7656441717296032"
  },
  {
    "symbol": "FGI",
    "name": "Fear & Greed Index",
    "price": 12,
    "h24": 39
  }
]