[
  {
    "symbol": "BTC",
    "name": "Bitcoin",
    "price": "71157.68748115413",
    "h24": "-3.631237634049504"
  },
  {
    "symbol": "ETH",
    "name": "Ethereum",
    "price": "1995.399978603972",
    "h24": "-0.9265104286660076"
  },
  {
    "symbol": "SOL",
    "name": "Solana",
    "price": "80.872263052418",
    "h24": "-2.3340484864146473"
  },
  {
    "symbol": "BNB",
    "name": "BNB",
    "price": "690.791017702786",
    "h24": "-2.9751857925876206"
  },
  {
    "symbol": "GNO",
    "name": "Gnosis",
    "price": "181.211835270816",
    "h24": "58.10460645149987"
  },
  {
    "symbol": "LAB",
    "name": "LAB",
    "price": "16.509557987455",
    "h24": "56.70291808139351"
  },
  {
    "symbol": "H",
    "name": "Humanity Protocol",
    "price": "0.704073460838",
    "h24": "36.36022320252703"
  },
  {
    "symbol": "WLD",
    "name": "World",
    "price": "0.434898235241",
    "h24": "21.644650716410652"
  },
  {
    "symbol": "SIREN",
    "name": "SIREN",
    "price": "0.592272104233",
    "h24": "14.909274572402904"
  },
  {
    "symbol": "NEAR",
    "name": "Near Protocol",
    "price": "2.587027477111",
    "h24": "10.873759265373998"
  },
  {
    "symbol": "M",
    "name": "MemeCore",
    "price": "3.225005954176",
    "h24": "8.043958706471354"
  },
  {
    "symbol": "GRAM",
    "name": "Gram (prev. Toncoin)",
    "price": "2.064643767526",
    "h24": "7.357699334676954"
  },
  {
    "symbol": "INJ",
    "name": "Injective",
    "price": "6.934295339877",
    "h24": "6.777658497084375"
  },
  {
    "symbol": "ICP",
    "name": "Internet Computer",
    "price": "2.898835376643",
    "h24": "5.206482143149478"
  },
  {
    "symbol": "JUP",
    "name": "Jupiter",
    "price": "0.201909794344",
    "h24": "4.868426889346918"
  },
  {
    "symbol": "UB",
    "name": "Unibase",
    "price": "0.192506697883",
    "h24": "4.834542036107671"
  },
  {
    "symbol": "FGI",
    "name": "Fear & Greed Index",
    "price": 23,
    "h24": 49
  }
]