[
  {
    "symbol": "BTC",
    "name": "Bitcoin",
    "price": "77468.55095148725",
    "h24": "0.7742561715904789"
  },
  {
    "symbol": "ETH",
    "name": "Ethereum",
    "price": "2114.205591905825",
    "h24": "-0.17217141626936572"
  },
  {
    "symbol": "SOL",
    "name": "Solana",
    "price": "85.861381909113",
    "h24": "-0.3859916240511143"
  },
  {
    "symbol": "BNB",
    "name": "BNB",
    "price": "661.084966608936",
    "h24": "0.3603770013688862"
  },
  {
    "symbol": "UB",
    "name": "Unibase",
    "price": "0.175368751897",
    "h24": "21.330350228260926"
  },
  {
    "symbol": "DEXE",
    "name": "DeXe",
    "price": "17.448082740348",
    "h24": "20.590657815652243"
  },
  {
    "symbol": "H",
    "name": "Humanity Protocol",
    "price": "0.25028495724",
    "h24": "20.237451873899346"
  },
  {
    "symbol": "STABLE",
    "name": "Stable",
    "price": "0.037950798031",
    "h24": "12.930346566480228"
  },
  {
    "symbol": "MORPHO",
    "name": "Morpho",
    "price": "2.395980114037",
    "h24": "10.105931491451546"
  },
  {
    "symbol": "XDC",
    "name": "XDC Network",
    "price": "0.033961345054",
    "h24": "9.630728799412537"
  },
  {
    "symbol": "EDGE",
    "name": "edgeX",
    "price": "1.377672230229",
    "h24": "9.156388001204828"
  },
  {
    "symbol": "ZEC",
    "name": "Zcash",
    "price": "669.90067927987",
    "h24": "4.334709864977609"
  },
  {
    "symbol": "M",
    "name": "MemeCore",
    "price": "2.971689378215",
    "h24": "3.5502557009892732"
  },
  {
    "symbol": "RENDER",
    "name": "Render",
    "price": "2.041512607494",
    "h24": "3.510983802834927"
  },
  {
    "symbol": "LUNC",
    "name": "Terra Classic",
    "price": "0.000082622506",
    "h24": "3.2835832911081884"
  },
  {
    "symbol": "NEAR",
    "name": "Near Protocol",
    "price": "2.430719684629",
    "h24": "3.190575749540781"
  },
  {
    "symbol": "FGI",
    "name": "Fear & Greed Index",
    "price": 30,
    "h24": 35
  }
]