[
  {
    "symbol": "BTC",
    "name": "Bitcoin",
    "price": "90657.2486025456",
    "h24": "0.25895526829433735"
  },
  {
    "symbol": "ETH",
    "name": "Ethereum",
    "price": "3095.865540435792",
    "h24": "0.04723565581667447"
  },
  {
    "symbol": "SOL",
    "name": "Solana",
    "price": "136.685418897994",
    "h24": "-1.3639832498067663"
  },
  {
    "symbol": "BNB",
    "name": "BNB",
    "price": "900.876249792821",
    "h24": "1.210551581958581"
  },
  {
    "symbol": "POL",
    "name": "POL (ex-MATIC)",
    "price": "0.169525505317",
    "h24": "16.052743438471804"
  },
  {
    "symbol": "STX",
    "name": "Stacks",
    "price": "0.381216670755",
    "h24": "10.414580223466762"
  },
  {
    "symbol": "PUMP",
    "name": "pump.fun",
    "price": "0.002350554747",
    "h24": "8.187605924297428"
  },
  {
    "symbol": "MORPHO",
    "name": "Morpho",
    "price": "1.297997727028",
    "h24": "6.750492289170231"
  },
  {
    "symbol": "ATOM",
    "name": "Cosmos Hub",
    "price": "2.615068266424",
    "h24": "6.433075098243385"
  },
  {
    "symbol": "RENDER",
    "name": "Render",
    "price": "2.360557038719",
    "h24": "6.425200264103568"
  },
  {
    "symbol": "VIRTUAL",
    "name": "Virtuals Protocol",
    "price": "1.077548693302",
    "h24": "3.7071738029060595"
  },
  {
    "symbol": "XTZ",
    "name": "Tezos",
    "price": "0.597448116541",
    "h24": "3.121334467837255"
  },
  {
    "symbol": "M",
    "name": "MemeCore",
    "price": "1.663455182736",
    "h24": "2.6404020958070227"
  },
  {
    "symbol": "MYX",
    "name": "MYX Finance",
    "price": "5.001837549286",
    "h24": "2.5486097829929357"
  },
  {
    "symbol": "CAKE",
    "name": "PancakeSwap",
    "price": "1.99543006591",
    "h24": "2.507170797547148"
  },
  {
    "symbol": "SUI",
    "name": "Sui",
    "price": "1.830684885677",
    "h24": "2.325416749617327"
  },
  {
    "symbol": "FGI",
    "name": "Fear & Greed Index",
    "price": 25,
    "h24": 36
  }
]