[
  {
    "symbol": "BTC",
    "name": "Bitcoin",
    "price": "109973.005860307940",
    "h24": "-7.728840069525986"
  },
  {
    "symbol": "ETH",
    "name": "Ethereum",
    "price": "3856.929228101089",
    "h24": "-12.423248612181373"
  },
  {
    "symbol": "SOL",
    "name": "Solana",
    "price": "187.954956749054",
    "h24": "0.8482582440848597"
  },
  {
    "symbol": "BNB",
    "name": "BNB",
    "price": "1082.714341851856",
    "h24": "-0.012192673969152985"
  },
  {
    "symbol": "TAO",
    "name": "Bittensor",
    "price": "480.459143436034",
    "h24": "15.976858980644568"
  },
  {
    "symbol": "ZEC",
    "name": "Zcash",
    "price": "379.478377990188",
    "h24": "14.493852453496832"
  },
  {
    "symbol": "ASTER",
    "name": "Aster (prev. Astherus)",
    "price": "0.991739029786",
    "h24": "9.153449797452467"
  },
  {
    "symbol": "AERO",
    "name": "Aerodrome",
    "price": "1.093796760388",
    "h24": "8.603670916893174"
  },
  {
    "symbol": "TON",
    "name": "Toncoin",
    "price": "2.258428116029",
    "h24": "5.125063105022868"
  },
  {
    "symbol": "CRO",
    "name": "Cronos",
    "price": "0.147729910857",
    "h24": "3.782960825729188"
  },
  {
    "symbol": "MORPHO",
    "name": "Morpho",
    "price": "1.993866739906",
    "h24": "3.396745182044701"
  },
  {
    "symbol": "ETC",
    "name": "Ethereum Classic",
    "price": "15.807189569849",
    "h24": "3.2037654158094524"
  },
  {
    "symbol": "FLOKI",
    "name": "FLOKI",
    "price": "0.000069046801",
    "h24": "2.90686538930353"
  },
  {
    "symbol": "XLM",
    "name": "Stellar",
    "price": "0.308326309062",
    "h24": "2.899457525955719"
  },
  {
    "symbol": "LTC",
    "name": "Litecoin",
    "price": "95.452085546274",
    "h24": "2.7650478090278616"
  },
  {
    "symbol": "BONK",
    "name": "Bonk",
    "price": "0.000013905523",
    "h24": "2.7276963694789726"
  },
  {
    "symbol": "FGI",
    "name": "Fear & Greed Index",
    "price": 29,
    "h24": 30
  }
]