[
  {
    "symbol": "BTC",
    "name": "Bitcoin",
    "price": "73713.3061169029",
    "h24": "-0.9819087226029515"
  },
  {
    "symbol": "ETH",
    "name": "Ethereum",
    "price": "2293.234687370656",
    "h24": "-2.1381146684279297"
  },
  {
    "symbol": "SOL",
    "name": "Solana",
    "price": "84.333133104823",
    "h24": "-0.09237618158482969"
  },
  {
    "symbol": "BNB",
    "name": "BNB",
    "price": "616.632371699709",
    "h24": "-0.5716205118729033"
  },
  {
    "symbol": "RAVE",
    "name": "RaveDAO",
    "price": "17.044502394276",
    "h24": "42.46564006734029"
  },
  {
    "symbol": "M",
    "name": "MemeCore",
    "price": "3.776838136392",
    "h24": "30.631681730122917"
  },
  {
    "symbol": "EDGE",
    "name": "edgeX",
    "price": "1.215215491699",
    "h24": "16.4937080307767"
  },
  {
    "symbol": "DOT",
    "name": "Polkadot",
    "price": "1.276243410418",
    "h24": "9.00948357474154"
  },
  {
    "symbol": "CHZ",
    "name": "Chiliz",
    "price": "0.042298371712",
    "h24": "7.900874508571548"
  },
  {
    "symbol": "FIL",
    "name": "Filecoin",
    "price": "0.972824446435",
    "h24": "7.225712233157631"
  },
  {
    "symbol": "ARB",
    "name": "Arbitrum",
    "price": "0.119306548189",
    "h24": "5.297261703746025"
  },
  {
    "symbol": "APT",
    "name": "Aptos",
    "price": "0.920680095888",
    "h24": "4.303550619990546"
  },
  {
    "symbol": "STX",
    "name": "Stacks",
    "price": "0.232409413754",
    "h24": "3.7570476624986857"
  },
  {
    "symbol": "TRUMP",
    "name": "OFFICIAL TRUMP",
    "price": "2.924539723379",
    "h24": "3.5112100138246523"
  },
  {
    "symbol": "WLD",
    "name": "World",
    "price": "0.30814007662",
    "h24": "3.4650387203189066"
  },
  {
    "symbol": "XDC",
    "name": "XDC Network",
    "price": "0.031702346375",
    "h24": "2.912647473450984"
  },
  {
    "symbol": "FGI",
    "name": "Fear & Greed Index",
    "price": 23,
    "h24": 36
  }
]