[
  {
    "symbol": "BTC",
    "name": "Bitcoin",
    "price": "71200.52985135726",
    "h24": "-0.5504097399881134"
  },
  {
    "symbol": "ETH",
    "name": "Ethereum",
    "price": "2186.21596628592",
    "h24": "-2.711158926916401"
  },
  {
    "symbol": "SOL",
    "name": "Solana",
    "price": "82.323107549943",
    "h24": "-2.7725899572664168"
  },
  {
    "symbol": "BNB",
    "name": "BNB",
    "price": "602.439270889195",
    "h24": "-1.6421866754575505"
  },
  {
    "symbol": "SIREN",
    "name": "SIREN",
    "price": "0.611204720654",
    "h24": "8.115213147289966"
  },
  {
    "symbol": "RAIN",
    "name": "Rain",
    "price": "0.00801055817",
    "h24": "5.866736853210988"
  },
  {
    "symbol": "DEXE",
    "name": "DeXe",
    "price": "7.992176760766",
    "h24": "5.03452304964318"
  },
  {
    "symbol": "JST",
    "name": "Just",
    "price": "0.06529092368",
    "h24": "2.9212116665033863"
  },
  {
    "symbol": "M",
    "name": "MemeCore",
    "price": "2.695531584448",
    "h24": "2.4996267647830797"
  },
  {
    "symbol": "CC",
    "name": "Canton Network",
    "price": "0.147435057678",
    "h24": "2.430296623132149"
  },
  {
    "symbol": "BGB",
    "name": "Bitget Token",
    "price": "1.914928739347",
    "h24": "1.901940561405328"
  },
  {
    "symbol": "BDX",
    "name": "Beldex",
    "price": "0.080138614393",
    "h24": "0.809635464776984"
  },
  {
    "symbol": "CHZ",
    "name": "Chiliz",
    "price": "0.039127332861",
    "h24": "0.7465842694182515"
  },
  {
    "symbol": "NEXO",
    "name": "Nexo",
    "price": "0.879619044114",
    "h24": "0.2699515767890217"
  },
  {
    "symbol": "ATOM",
    "name": "Cosmos Hub",
    "price": "1.789816040705",
    "h24": "0.2688909425810322"
  },
  {
    "symbol": "HTX",
    "name": "HTX DAO",
    "price": "0.000001746455",
    "h24": "0.25090638568519086"
  },
  {
    "symbol": "FGI",
    "name": "Fear & Greed Index",
    "price": 14,
    "h24": 34
  }
]