[
  {
    "symbol": "BTC",
    "name": "Bitcoin",
    "price": "65742.36890718646",
    "h24": "-1.306406384465269"
  },
  {
    "symbol": "ETH",
    "name": "Ethereum",
    "price": "1794.62348554813",
    "h24": "-1.404042897001253"
  },
  {
    "symbol": "SOL",
    "name": "Solana",
    "price": "74.06831114349",
    "h24": "-1.321699448753527"
  },
  {
    "symbol": "BNB",
    "name": "BNB",
    "price": "607.477869583837",
    "h24": "-2.1060718624613037"
  },
  {
    "symbol": "LAB",
    "name": "LAB",
    "price": "12.542268068424",
    "h24": "28.969070467506125"
  },
  {
    "symbol": "SKYAI",
    "name": "SKYAI",
    "price": "0.443737635933",
    "h24": "25.136436828076125"
  },
  {
    "symbol": "UNI",
    "name": "Uniswap",
    "price": "3.280679471701",
    "h24": "21.30436577050943"
  },
  {
    "symbol": "WLD",
    "name": "World",
    "price": "0.667756329166",
    "h24": "12.178167721315477"
  },
  {
    "symbol": "AERO",
    "name": "Aerodrome",
    "price": "0.473393344078",
    "h24": "9.848888363076476"
  },
  {
    "symbol": "HYPE",
    "name": "Hyperliquid",
    "price": "72.969471840507",
    "h24": "8.06485850995029"
  },
  {
    "symbol": "M",
    "name": "MemeCore",
    "price": "3.118370569059",
    "h24": "5.693304570153908"
  },
  {
    "symbol": "LIT",
    "name": "Lighter",
    "price": "1.779289725779",
    "h24": "4.778557723673947"
  },
  {
    "symbol": "JST",
    "name": "Just",
    "price": "0.081647145733",
    "h24": "3.397585145281366"
  },
  {
    "symbol": "ATOM",
    "name": "Cosmos Hub",
    "price": "2.005336002952",
    "h24": "2.5768999161940913"
  },
  {
    "symbol": "AAVE",
    "name": "Aave",
    "price": "76.24808761256",
    "h24": "2.379278410280927"
  },
  {
    "symbol": "RAIN",
    "name": "Rain",
    "price": "0.014133922138",
    "h24": "2.2572782212794524"
  },
  {
    "symbol": "FGI",
    "name": "Fear & Greed Index",
    "price": 23,
    "h24": 51
  }
]