[
  {
    "symbol": "BTC",
    "name": "Bitcoin",
    "price": "74399.53253672527",
    "h24": "4.974946851560053"
  },
  {
    "symbol": "ETH",
    "name": "Ethereum",
    "price": "2371.111258427149",
    "h24": "6.755101310039415"
  },
  {
    "symbol": "SOL",
    "name": "Solana",
    "price": "85.754891164243",
    "h24": "4.728299283659776"
  },
  {
    "symbol": "BNB",
    "name": "BNB",
    "price": "616.309914272791",
    "h24": "2.9843253584528133"
  },
  {
    "symbol": "RAVE",
    "name": "RaveDAO",
    "price": "14.934401857334",
    "h24": "58.91632493868957"
  },
  {
    "symbol": "VVV",
    "name": "Venice Token",
    "price": "9.327787276051",
    "h24": "12.249387568793619"
  },
  {
    "symbol": "MON",
    "name": "Monad",
    "price": "0.037102681421",
    "h24": "10.6820576135911"
  },
  {
    "symbol": "PENGU",
    "name": "Pudgy Penguins",
    "price": "0.007162468378",
    "h24": "10.569418588251724"
  },
  {
    "symbol": "ALGO",
    "name": "Algorand",
    "price": "0.111161141486",
    "h24": "8.933481221227186"
  },
  {
    "symbol": "PUMP",
    "name": "pump.fun",
    "price": "0.001929872876",
    "h24": "7.836233518465568"
  },
  {
    "symbol": "HYPE",
    "name": "Hyperliquid",
    "price": "44.888136252775",
    "h24": "7.311064005065973"
  },
  {
    "symbol": "AAVE",
    "name": "Aave",
    "price": "100.627285759121",
    "h24": "7.271918273842371"
  },
  {
    "symbol": "PEPE",
    "name": "Pepe",
    "price": "0.000003727019",
    "h24": "7.161774350714231"
  },
  {
    "symbol": "WLD",
    "name": "World",
    "price": "0.315383462267",
    "h24": "6.93158027091935"
  },
  {
    "symbol": "BONK",
    "name": "Bonk",
    "price": "0.000005960913",
    "h24": "6.129008538337772"
  },
  {
    "symbol": "CC",
    "name": "Canton Network",
    "price": "0.15737841733",
    "h24": "6.110906200067107"
  },
  {
    "symbol": "FGI",
    "name": "Fear & Greed Index",
    "price": 21,
    "h24": 40
  }
]