[
  {
    "symbol": "BTC",
    "name": "Bitcoin",
    "price": "65423.30609506003",
    "h24": "1.043705803968603"
  },
  {
    "symbol": "ETH",
    "name": "Ethereum",
    "price": "1932.15190471108",
    "h24": "2.8066536279474"
  },
  {
    "symbol": "SOL",
    "name": "Solana",
    "price": "78.082180394092",
    "h24": "0.7735075442861897"
  },
  {
    "symbol": "BNB",
    "name": "BNB",
    "price": "581.145150279399",
    "h24": "-0.32531912654143597"
  },
  {
    "symbol": "PUMP",
    "name": "pump.fun",
    "price": "0.001661155918",
    "h24": "11.791320756150286"
  },
  {
    "symbol": "ETHFI",
    "name": "ether.fi",
    "price": "0.436497295931",
    "h24": "8.300050746205404"
  },
  {
    "symbol": "ZEC",
    "name": "Zcash",
    "price": "572.172576527428",
    "h24": "6.550396874052487"
  },
  {
    "symbol": "ONDO",
    "name": "Ondo Finance",
    "price": "0.333351922082",
    "h24": "4.962248670149172"
  },
  {
    "symbol": "VIRTUAL",
    "name": "Virtuals Protocol",
    "price": "0.612984670749",
    "h24": "4.917573530042342"
  },
  {
    "symbol": "PENGU",
    "name": "Pudgy Penguins",
    "price": "0.006237671512",
    "h24": "4.6651101922557805"
  },
  {
    "symbol": "M",
    "name": "MemeCore",
    "price": "1.283599506862",
    "h24": "4.573483483952703"
  },
  {
    "symbol": "HYPE",
    "name": "Hyperliquid",
    "price": "67.91347004325",
    "h24": "4.49735235944942"
  },
  {
    "symbol": "CC",
    "name": "Canton Network",
    "price": "0.138125326513",
    "h24": "4.122604929713182"
  },
  {
    "symbol": "RAIN",
    "name": "Rain",
    "price": "0.01461612159",
    "h24": "3.3296040700904013"
  },
  {
    "symbol": "BEAT",
    "name": "Audiera",
    "price": "2.641712008018",
    "h24": "2.8202507351103634"
  },
  {
    "symbol": "INJ",
    "name": "Injective",
    "price": "5.15106504507",
    "h24": "2.6440666335085474"
  },
  {
    "symbol": "FGI",
    "name": "Fear & Greed Index",
    "price": 25,
    "h24": 47
  }
]