[
  {
    "symbol": "BTC",
    "name": "Bitcoin",
    "price": "110883.302109166850",
    "h24": "-6.96506999608393"
  },
  {
    "symbol": "ETH",
    "name": "Ethereum",
    "price": "4032.961175754597",
    "h24": "-8.426207130672314"
  },
  {
    "symbol": "SOL",
    "name": "Solana",
    "price": "192.280680517481",
    "h24": "1.8748251756401983"
  },
  {
    "symbol": "BNB",
    "name": "BNB",
    "price": "1113.754257526462",
    "h24": "1.5738573649497705"
  },
  {
    "symbol": "FLOKI",
    "name": "FLOKI",
    "price": "0.000082440864",
    "h24": "24.930799685275883"
  },
  {
    "symbol": "ZEC",
    "name": "Zcash",
    "price": "253.286265329338",
    "h24": "17.072887453470017"
  },
  {
    "symbol": "LINK",
    "name": "ChainLink",
    "price": "19.021121851077",
    "h24": "11.338866801816444"
  },
  {
    "symbol": "SPX",
    "name": "SPX6900",
    "price": "1.058874820722",
    "h24": "9.626204402665401"
  },
  {
    "symbol": "FET",
    "name": "Artificial Superintelligence Alliance",
    "price": "0.289214081761",
    "h24": "9.342480847424255"
  },
  {
    "symbol": "XDC",
    "name": "XDC Network",
    "price": "0.064973572799",
    "h24": "8.035826783659562"
  },
  {
    "symbol": "AERO",
    "name": "Aerodrome",
    "price": "0.849472307029",
    "h24": "7.29904800359649"
  },
  {
    "symbol": "HBAR",
    "name": "Hedera",
    "price": "0.178353690743",
    "h24": "6.922404321346687"
  },
  {
    "symbol": "BONK",
    "name": "Bonk",
    "price": "0.000015343259",
    "h24": "6.435208391805925"
  },
  {
    "symbol": "FIL",
    "name": "Filecoin",
    "price": "1.602883276802",
    "h24": "6.383749804244813"
  },
  {
    "symbol": "IMX",
    "name": "Immutable",
    "price": "0.537620632748",
    "h24": "6.328909472979064"
  },
  {
    "symbol": "M",
    "name": "MemeCore",
    "price": "2.059231267615",
    "h24": "5.931067512233974"
  },
  {
    "symbol": "FGI",
    "name": "Fear & Greed Index",
    "price": 29,
    "h24": 25
  }
]