[
  {
    "symbol": "BTC",
    "name": "Bitcoin",
    "price": "70617.58866325143",
    "h24": "-1.8219200917240805"
  },
  {
    "symbol": "ETH",
    "name": "Ethereum",
    "price": "2076.089039501825",
    "h24": "-1.6063353685876922"
  },
  {
    "symbol": "SOL",
    "name": "Solana",
    "price": "87.314772809975",
    "h24": "-2.2573273799574105"
  },
  {
    "symbol": "BNB",
    "name": "BNB",
    "price": "652.336121140957",
    "h24": "-2.266688752961228"
  },
  {
    "symbol": "SIREN",
    "name": "SIREN",
    "price": "0.601880010005",
    "h24": "5.660776561224308"
  },
  {
    "symbol": "CC",
    "name": "Canton Network",
    "price": "0.154204195768",
    "h24": "5.519540710009217"
  },
  {
    "symbol": "TRUMP",
    "name": "OFFICIAL TRUMP",
    "price": "3.890119665263",
    "h24": "5.495291905632351"
  },
  {
    "symbol": "M",
    "name": "MemeCore",
    "price": "1.526205587363",
    "h24": "4.600907085670525"
  },
  {
    "symbol": "RIVER",
    "name": "River",
    "price": "21.550296302108",
    "h24": "4.27998519233035"
  },
  {
    "symbol": "JST",
    "name": "Just",
    "price": "0.055258889461",
    "h24": "2.783144713198859"
  },
  {
    "symbol": "STABLE",
    "name": "Stable",
    "price": "0.029401412104",
    "h24": "2.4466061689295504"
  },
  {
    "symbol": "XMR",
    "name": "Monero",
    "price": "363.312631692682",
    "h24": "1.6489163832153089"
  },
  {
    "symbol": "HTX",
    "name": "HTX DAO",
    "price": "0.000001623034",
    "h24": "1.4220663047709865"
  },
  {
    "symbol": "QNT",
    "name": "Quant",
    "price": "65.557856152038",
    "h24": "1.3957808755730516"
  },
  {
    "symbol": "TRX",
    "name": "TRON",
    "price": "0.293469315898",
    "h24": "1.3218581864919052"
  },
  {
    "symbol": "ATOM",
    "name": "Cosmos Hub",
    "price": "1.869329477876",
    "h24": "1.279530605658659"
  },
  {
    "symbol": "FGI",
    "name": "Fear & Greed Index",
    "price": 16,
    "h24": 44
  }
]